{"path":"/Users/adolphe/Desktop/.git/SP2_Team1","projectCount":1,"lastUsed":1509798061883,"recentFiles":[{"name":"Personeel.java","path":"/HR/src/logic","parentWorkspace":"/Users/adolphe/Desktop/.git/SP2_Team1","lastModified":1509797879391,"locationURI":"file:/Users/adolphe/Desktop/.git/SP2_Team1/HR/src/logic/Personeel.java"},{"name":"Event.java","path":"/HR/src/logic","parentWorkspace":"/Users/adolphe/Desktop/.git/SP2_Team1","lastModified":1509797542385},{"name":"Vraag.java","path":"/HR/src/logic","parentWorkspace":"/Users/adolphe/Desktop/.git/SP2_Team1","lastModified":0},{"name":"Vaardigheid.java","path":"/HR/src/logic","parentWorkspace":"/Users/adolphe/Desktop/.git/SP2_Team1","lastModified":1509701492614,"locationURI":"file:/Users/adolphe/Desktop/.git/SP2_Team1/HR/src/logic/Vaardigheid.java"}]}